{
  "23-65-902-2-516-3421": {
    "position": {
      "x": 0,
      "y": 2,
      "z": 0
    },
    "artworkScale": {
      "x": 1,
      "y": 1,
      "z": 1
    },
    "platform": {
      "x": -114.4364,
      "y": 5.334512,
      "z": 187.5804
    },
    "rotation": {
      "x": 290.4745,
      "y": 108.7383,
      "z": 252.7941
    },
    "colideScale": {
      "x": 10,
      "y": 10,
      "z": 10
    },
    "url": "https://raw.githubusercontent.com/alecjacobson/computer-graphics-meshes/master/data/bob.obj",
    "description": "\n\n\n\n",
    "uploadOptions": "True/True/True/True/False/",
    "verifiedStatus": "True",
    "id": "23-65-902-2-516-3421"
  }
}